dpdc_amr/TunedModel.keras
dpdc_amr/__init__.py
dpdc_amr/app.py
dpdc_amr/auth_utils.py
dpdc_amr/digitExtractions.py
dpdc_amr/testMyML.py
dpdc_amr/utils.py
dpdc_amr/static/favicon.ico
dpdc_amr/static/jquery-ui.css
dpdc_amr/static/jquery.min.js
dpdc_amr/static/xlsx.full.min.js
dpdc_amr/static/images/DPDC.png
dpdc_amr/static/uploads/1042303_201901_KWH_SR.jpg
dpdc_amr/static/uploads/OIP.jpg
dpdc_amr/static/uploads/readme.md
dpdc_amr/static/waitme/img.svg
dpdc_amr/static/waitme/waitMe.css
dpdc_amr/static/waitme/waitMe.js
dpdc_amr/static/waitme/waitMe.min.css
dpdc_amr/static/waitme/waitMe.min.js
dpdc_amr/static/waitme/waitMeFunc.js
dpdc_amr/templates/batch_proc.html
dpdc_amr/templates/index.html
dpdc_amr/weights/best.pt
dpdc_amr/weights/best_cls.pt
dpdc_amr-1.4.3.dist-info/METADATA
dpdc_amr-1.4.3.dist-info/WHEEL
dpdc_amr-1.4.3.dist-info/entry_points.txt
dpdc_amr-1.4.3.dist-info/top_level.txt
dpdc_amr-1.4.3.dist-info/RECORD
