Metadata-Version: 2.1
Name: dpdc_amr
Version: 1.4.3
Summary: Automated Meter Reading Using DeepLearning
Home-page: https://github.com/mamun01714/flask
Author: Md. Mamunur Rashed
Author-email: mamunur.rashed@dpdc.gov.bd
Classifier: Programming Language :: Python :: 3
Classifier: License :: OSI Approved :: MIT License
Classifier: Operating System :: OS Independent
Requires-Python: >=3.10
Requires-Dist: absl-py==2.1.0
Requires-Dist: astunparse==1.6.3
Requires-Dist: blinker==1.9.0
Requires-Dist: certifi==2024.8.30
Requires-Dist: chardet==5.2.0
Requires-Dist: charset-normalizer==3.4.0
Requires-Dist: click==8.1.7
Requires-Dist: colorama==0.4.6
Requires-Dist: contourpy==1.3.1
Requires-Dist: cycler==0.12.1
Requires-Dist: filelock==3.16.1
Requires-Dist: Flask==3.1.0
Requires-Dist: flatbuffers==24.3.25
Requires-Dist: fonttools==4.55.0
Requires-Dist: fsspec==2024.10.0
Requires-Dist: gast==0.6.0
Requires-Dist: google-pasta==0.2.0
Requires-Dist: grpcio==1.68.0
Requires-Dist: h5py==3.12.1
Requires-Dist: idna==3.10
Requires-Dist: itsdangerous==2.2.0
Requires-Dist: Jinja2==3.1.4
Requires-Dist: keras==3.6.0
Requires-Dist: kiwisolver==1.4.7
Requires-Dist: libclang==18.1.1
Requires-Dist: Markdown==3.7
Requires-Dist: markdown-it-py==3.0.0
Requires-Dist: MarkupSafe==3.0.2
Requires-Dist: matplotlib==3.9.2
Requires-Dist: mdurl==0.1.2
Requires-Dist: ml-dtypes==0.4.1
Requires-Dist: mpmath==1.3.0
Requires-Dist: namex==0.0.8
Requires-Dist: networkx==3.4.2
Requires-Dist: numpy==2.0.2
Requires-Dist: opencv-python==4.10.0.84
Requires-Dist: opt-einsum==3.4.0
Requires-Dist: optree==0.13.1
Requires-Dist: packaging==24.2
Requires-Dist: pandas==2.2.3
Requires-Dist: pillow==11.0.0
Requires-Dist: protobuf==5.28.3
Requires-Dist: psutil==6.1.0
Requires-Dist: py-cpuinfo==9.0.0
Requires-Dist: Pygments==2.18.0
Requires-Dist: pyparsing==3.2.0
Requires-Dist: python-dateutil==2.9.0.post0
Requires-Dist: pytz==2024.2
Requires-Dist: PyYAML==6.0.2
Requires-Dist: requests==2.32.3
Requires-Dist: rich==13.9.4
Requires-Dist: scipy==1.14.1
Requires-Dist: seaborn==0.13.2
Requires-Dist: six==1.16.0
Requires-Dist: sympy==1.13.1
Requires-Dist: termcolor==2.5.0
Requires-Dist: torch==2.5.1
Requires-Dist: torchvision==0.20.1
Requires-Dist: tqdm==4.67.0
Requires-Dist: typing-extensions==4.12.2
Requires-Dist: tzdata==2024.2
Requires-Dist: ultralytics==8.3.35
Requires-Dist: ultralytics-thop==2.0.12
Requires-Dist: urllib3==2.2.3
Requires-Dist: waitress==3.0.2
Requires-Dist: Werkzeug==3.1.3
Requires-Dist: wrapt==1.17.0
